telegram_async/__init__.py
telegram_async/bot.py
telegram_async/buttons.py
telegram_async/callback.py
telegram_async/client.py
telegram_async/context.py
telegram_async/decorators.py
telegram_async/dispatcher.py
telegram_async/docs.py
telegram_async/logger.py
telegram_async/middleware.py
telegram_async/roles.py
telegram_async/server.py
telegram_async/storage.py
telegram_async/tasks.py
telegram_async/throttling.py
telegram_async-0.1.2.1.dist-info/licenses/LICENSE
telegram_async-0.1.2.1.dist-info/METADATA
telegram_async-0.1.2.1.dist-info/WHEEL
telegram_async-0.1.2.1.dist-info/top_level.txt
telegram_async-0.1.2.1.dist-info/RECORD
