Metadata-Version: 2.4
Name: telegram-async
Version: 0.1.2.1
Summary: Asynchronous Telegram bot framework with throttling, callbacks, and middleware
Author-email: Denys <ostrovskyidenys30@gmail.com>
License: MIT
Keywords: telegram,async,bot,framework
Classifier: Programming Language :: Python :: 3
Classifier: License :: OSI Approved :: MIT License
Classifier: Operating System :: OS Independent
License-File: LICENSE
Requires-Dist: aiohttp>=3.13.3
Requires-Dist: rich>=14.2.0
Dynamic: license-file
